tree_sitter_make/__init__.pyi
tree_sitter_make/binding.c
tree_sitter_make/__init__.py
tree_sitter_make/py.typed
tree_sitter_make/_binding.abi3.so
tree_sitter_make/queries/highlights.scm
tree_sitter_make-1.1.1.dist-info/RECORD
tree_sitter_make-1.1.1.dist-info/LICENSE
tree_sitter_make-1.1.1.dist-info/WHEEL
tree_sitter_make-1.1.1.dist-info/top_level.txt
tree_sitter_make-1.1.1.dist-info/METADATA
